pyp3d/__init__.py
pyp3d/main/__init__.py
pyp3d-2.0.19.dist-info/METADATA
pyp3d-2.0.19.dist-info/WHEEL
pyp3d-2.0.19.dist-info/top_level.txt
pyp3d-2.0.19.dist-info/RECORD
