Metadata-Version: 2.1
Name: pyp3d
Version: 2.0.19
Summary: Python interface of P3D.
Home-page: UNKNOWN
Author: Copyright (C), 2020, Beijing GLory PKPM Technology. Co., Ltd. All rights reserved.
Author-email: youqi@cabrtech.com
License: UNKNOWN
Platform: UNKNOWN
Classifier: Programming Language :: Python :: 3
Classifier: License :: Free For Educational Use
Classifier: Operating System :: Microsoft :: Windows
Requires-Python: >=3.8
Requires-Dist: pywin32
Requires-Dist: numpy (==1.19.3)
